gradec/__init__.py
gradec/_version.py
gradec/decode.py
gradec/fetcher.py
gradec/model.py
gradec/plot.py
gradec/segmentation.py
gradec/stats.py
gradec/transform.py
gradec/utils.py
gradec/tests/__init__.py
gradec/tests/conftest.py
gradec/tests/test_decode.py
gradec/tests/test_fetcher.py
gradec/tests/test_model.py
gradec/tests/test_plot.py
gradec/tests/test_segmentation.py
gradec-0.0.1rc5.dist-info/METADATA
gradec-0.0.1rc5.dist-info/WHEEL
gradec-0.0.1rc5.dist-info/licenses/LICENSE
gradec-0.0.1rc5.dist-info/RECORD
