Metadata-Version: 2.1
Name: gradec
Version: 0.0.1rc5
Summary: Meta-analytic gradient decoding
Project-URL: Homepage, https://github.com/JulioAPeraza/gradec
Project-URL: Documentation, https://gradec.readthedocs.io/en/latest/
Author: Gradec developers
Maintainer-email: Julio A Peraza <jperaza@fiu.edu>
License:                                  Apache License
License-File: LICENSE
Classifier: Development Status :: 3 - Alpha
Classifier: Environment :: Console
Classifier: Intended Audience :: Science/Research
Classifier: License :: OSI Approved :: Apache Software License
Classifier: Operating System :: OS Independent
Classifier: Programming Language :: Python :: 3.8
Classifier: Programming Language :: Python :: 3.9
Classifier: Programming Language :: Python :: 3.10
Classifier: Programming Language :: Python :: 3.11
Classifier: Topic :: Scientific/Engineering
Requires-Python: >=3.8
Requires-Dist: netneurotools>=0.2.4
Requires-Dist: neuromaps
Requires-Dist: nilearn<=0.10.2
Requires-Dist: nimare>=0.2.1
Requires-Dist: scipy
Requires-Dist: surfplot
Requires-Dist: wordcloud
Provides-Extra: all
Requires-Dist: gradec[dev,doc,test]; extra == 'all'
Provides-Extra: dev
Requires-Dist: black; extra == 'dev'
Requires-Dist: flake8-pyproject; extra == 'dev'
Requires-Dist: isort; extra == 'dev'
Requires-Dist: pre-commit; extra == 'dev'
Provides-Extra: devs
Requires-Dist: gradec[dev]; extra == 'devs'
Provides-Extra: doc
Requires-Dist: sphinx-argparse; extra == 'doc'
Requires-Dist: sphinx-copybutton; extra == 'doc'
Requires-Dist: sphinx-gallery; extra == 'doc'
Requires-Dist: sphinx-rtd-theme; extra == 'doc'
Requires-Dist: sphinx>=2.0; extra == 'doc'
Provides-Extra: docs
Requires-Dist: gradec[doc]; extra == 'docs'
Provides-Extra: min
Requires-Dist: nimare==0.2.1; extra == 'min'
Provides-Extra: minimum
Requires-Dist: gradec[min]; extra == 'minimum'
Provides-Extra: test
Requires-Dist: coverage; extra == 'test'
Requires-Dist: coveralls; extra == 'test'
Requires-Dist: flake8-black; extra == 'test'
Requires-Dist: flake8-docstrings; extra == 'test'
Requires-Dist: flake8-isort; extra == 'test'
Requires-Dist: flake8-pyproject; extra == 'test'
Requires-Dist: pytest; extra == 'test'
Requires-Dist: pytest-cov; extra == 'test'
Requires-Dist: pytest-env; extra == 'test'
Provides-Extra: tests
Requires-Dist: gradec[test]; extra == 'tests'
